COPYRIGHT
MANIFEST.in
Makefile
README
setup.py
test/__init__.py
test/__init__.pyc
test/test_compile.py
test/test_serve.py
test/__pycache__/test_compile.cpython-27-PYTEST.pyc
test/__pycache__/test_serve.cpython-27-PYTEST.pyc
tiddlywebplugins/__init__.py
tiddlywebplugins/privateer.py
tiddlywebplugins.privateer.egg-info/PKG-INFO
tiddlywebplugins.privateer.egg-info/SOURCES.txt
tiddlywebplugins.privateer.egg-info/dependency_links.txt
tiddlywebplugins.privateer.egg-info/namespace_packages.txt
tiddlywebplugins.privateer.egg-info/not-zip-safe
tiddlywebplugins.privateer.egg-info/requires.txt
tiddlywebplugins.privateer.egg-info/top_level.txt