Metadata-Version: 1.0
Name: tiddlywebplugins.privateer
Version: 0.7
Summary: Public access to private things.
Home-page: http://pypi.python.org/pypi/tiddlywebplugins.privateer
Author: Chris Dent
Author-email: cdent@peermore.com
License: BSD
Platform: Posix; MacOS X; Windows
